fastapi_telescope/__init__.py
fastapi_telescope/config.py
fastapi_telescope/db.py
fastapi_telescope/middleware.py
fastapi_telescope/router.py
fastapi_telescope/app/__init__.py
fastapi_telescope/app/dashboard/__init__.py
fastapi_telescope/app/dashboard/router.py
fastapi_telescope/app/dashboard/templates/dashboard.html
fastapi_telescope/app/dashboard/templates/components/DBQueries.js
fastapi_telescope/app/dashboard/templates/components/DBQueryDetail.js
fastapi_telescope/app/dashboard/templates/components/DashboardView.js
fastapi_telescope/app/dashboard/templates/components/HttpRequestDetail.js
fastapi_telescope/app/dashboard/templates/components/HttpRequests.js
fastapi_telescope/app/log_db_queries/__init__.py
fastapi_telescope/app/log_db_queries/router.py
fastapi_telescope/app/log_db_queries/schema.py
fastapi_telescope/app/log_http_request/__init__.py
fastapi_telescope/app/log_http_request/router.py
fastapi_telescope/app/log_http_request/schema.py
fastapi_telescope/models/__init__.py
fastapi_telescope/models/base.py
fastapi_telescope/models/log_db_query.py
fastapi_telescope/models/log_http_request.py
fastapi_telescope-0.0.14.dist-info/METADATA
fastapi_telescope-0.0.14.dist-info/WHEEL
fastapi_telescope-0.0.14.dist-info/licenses/LICENSE
fastapi_telescope-0.0.14.dist-info/RECORD
