Metadata-Version: 2.4
Name: fastapi_telescope
Version: 0.0.14
Summary: Middleware and tool for FastApi HTTP requests and DB queries debugging
Project-URL: Homepage, https://github.com/AlisaZobova/fastapi-telescope-pip
Author-email: Alisa Zobova <zobovaalice@gmail.com>
License-Expression: MIT
License-File: LICENSE
Keywords: debugging,fastapi
Classifier: Operating System :: OS Independent
Classifier: Programming Language :: Python :: 3
Requires-Python: >=3.9
Requires-Dist: aiofiles>=23.2.1
Requires-Dist: asyncpg>=0.30.0
Requires-Dist: fastapi-pagination>=0.12.34
Requires-Dist: fastapi>=0.115.8
Requires-Dist: jinja2>=3.1.2
Requires-Dist: loguru>=0.7.3
Requires-Dist: psycopg2-binary>=2.9.10
Requires-Dist: pydantic-settings>=2.8.0
Requires-Dist: pydantic>=2.10.6
Requires-Dist: python-dotenv>=1.0.1
Requires-Dist: pytz>=2025.1
Requires-Dist: sqlalchemy>=2.0.38
Requires-Dist: uvicorn<0.35.0,>=0.34.0
